{"index_version":"mini-kv-ttl-token-fixtures.v1","capability":"ttl_token_primitive","command":"SETNXEX key seconds value","schema_version":1,"read_only":false,"execution_allowed":true,"order_authoritative":false,"consumer_hint":"Node v160 idempotency vertical readiness review","semantics":{"success_response":"1","duplicate_response":"0","expired_token_can_be_claimed_again":true,"requires_positive_ttl_seconds":true,"value_required":true,"atomic_absent_claim":true},"wal":{"enabled_record":"SETEXAT key epoch_millis value","single_record_claim":true,"replay_drops_expired_token":true},"boundaries":["ttl token primitive only","not an order-authoritative store","not connected to Java transaction chain","does not change payment or inventory semantics","production idempotency ownership remains outside mini-kv"],"diagnostics":{"notes":["SETNXEX is a write command and must not be used by read-only release evidence capture","CHECKJSON SETNXEX can inspect the contract without executing the write","Node v160 may reference this file as mini-kv v61 token primitive evidence"]}}
